README.md
setup.py
aep_python_sdk_v3/__init__.py
aep_python_sdk_v3/aep_cloud_client.py
aep_python_sdk_v3/aep_request.py
aep_python_sdk_v3.egg-info/PKG-INFO
aep_python_sdk_v3.egg-info/SOURCES.txt
aep_python_sdk_v3.egg-info/dependency_links.txt
aep_python_sdk_v3.egg-info/requires.txt
aep_python_sdk_v3.egg-info/top_level.txt
aep_python_sdk_v3/client/__init__.py
aep_python_sdk_v3/client/aep_response.py
aep_python_sdk_v3/error/__init__.py
aep_python_sdk_v3/error/aep_api_exception.py
aep_python_sdk_v3/error/client_exception.py
aep_python_sdk_v3/error/error_code.py
aep_python_sdk_v3/error/error_msg.py
aep_python_sdk_v3/error/error_type.py
aep_python_sdk_v3/error/server_exception.py
aep_python_sdk_v3/https/__init__.py
aep_python_sdk_v3/https/body_format.py
aep_python_sdk_v3/https/format_type.py
aep_python_sdk_v3/https/http_request.py
aep_python_sdk_v3/https/method_type.py
aep_python_sdk_v3/utils/__init__.py
aep_python_sdk_v3/utils/aep_utils.py