Metadata-Version: 1.2
Name: aep-python-sdk-v3
Version: 1.1.3
Summary: aep sdk tool
Home-page: https://apicloud.inspur.com/
Author: Enzo Liang
Author-email: liangyzh@inspur.com
License: UNKNOWN
Keywords: sdk,tool
Platform: UNKNOWN
Classifier: Programming Language :: Python :: 3
Classifier: Operating System :: OS Independent
Requires-Python: >=3
